mbonig/aws_lambda_nodejs/__init__.py
mbonig/aws_lambda_nodejs/py.typed
mbonig/aws_lambda_nodejs/_jsii/__init__.py
mbonig/aws_lambda_nodejs/_jsii/nodejsfunction-plus@0.0.1.jsii.tgz
mbonig.aws_lambda_nodejs.NodejsFunctionPlus-0.0.1.dist-info/METADATA
mbonig.aws_lambda_nodejs.NodejsFunctionPlus-0.0.1.dist-info/WHEEL
mbonig.aws_lambda_nodejs.NodejsFunctionPlus-0.0.1.dist-info/top_level.txt
mbonig.aws_lambda_nodejs.NodejsFunctionPlus-0.0.1.dist-info/RECORD
