Metadata-Version: 2.1
Name: mbonig.aws-lambda-nodejs.NodejsFunctionPlus
Version: 0.0.1
Summary: The NodejsFunction from the @aws-cdk/aws-lambda-nodejs package but with the AWS_NODEJS_CONNECTION_REUSE_ENABLED automatically set.
Home-page: https://github.com/mbonig/nodejsfunction-plus.git
Author: Matthew Bonig<matthew.bonig@gmail.com>
License: MIT
Project-URL: Source, https://github.com/mbonig/nodejsfunction-plus.git
Platform: UNKNOWN
Classifier: Intended Audience :: Developers
Classifier: Operating System :: OS Independent
Classifier: Programming Language :: JavaScript
Classifier: Programming Language :: Python :: 3 :: Only
Classifier: Programming Language :: Python :: 3.6
Classifier: Programming Language :: Python :: 3.7
Classifier: Programming Language :: Python :: 3.8
Classifier: Typing :: Typed
Classifier: License :: OSI Approved
Requires-Python: >=3.6
Requires-Dist: jsii (~=1.0.0)
Requires-Dist: publication (>=0.0.3)
Requires-Dist: aws-cdk.aws-lambda (<2.0.0,>=1.25.0)
Requires-Dist: aws-cdk.aws-lambda-nodejs (<2.0.0,>=1.25.0)
Requires-Dist: aws-cdk.core (<2.0.0,>=1.25.0)
